set_loglevel/__init__.py
set_loglevel/set_loglevel.py
set_loglevel-0.1.1.dist-info/LICENSE
set_loglevel-0.1.1.dist-info/WHEEL
set_loglevel-0.1.1.dist-info/METADATA
set_loglevel-0.1.1.dist-info/RECORD
