Metadata-Version: 2.1
Name: set-loglevel
Version: 0.1.1
Summary: Return a loglevel (10, 20, etc.) taking ENV LOGLEVEL into account
Home-page: https://github.com/ffreemt/set-loglevel
License: MIT
Author: ffreemt
Requires-Python: >=3.8.3,<4.0.0
Classifier: License :: OSI Approved :: MIT License
Classifier: Programming Language :: Python :: 3
Classifier: Programming Language :: Python :: 3.10
Classifier: Programming Language :: Python :: 3.9
Requires-Dist: environs (>=9.5.0,<10.0.0)
Requires-Dist: logzero (>=1.7.0,<2.0.0)
Project-URL: Repository, https://github.com/ffreemt/set-loglevel
